tornado_rest/__init__.py
tornado_rest/apps/__init__.py
tornado_rest/apps/blog/__init__.py
tornado_rest/apps/blog/api.py
tornado_rest/apps/blog/handler.py
tornado_rest/apps/blog/route.py
tornado_rest/bin/__init__.py
tornado_rest/bin/tornado_rest.py
tornado_rest/common/__init__.py
tornado_rest/common/base_handler.py
tornado_rest/common/config.py
tornado_rest/config/__init__.py
tornado_rest/config/config.py
tornado_rest/core/__init__.py
tornado_rest/core/decorators.py
tornado_rest/core/encoders.py
tornado_rest/db/__init__.py
tornado_rest/db/models.py
tornado_rest/db/pool.py
tornado_rest/server/__init__.py
tornado_rest/server/base.py
tornado_rest/server/tornado_server.py
tornado_rest-0.0.1.dist-info/METADATA
tornado_rest-0.0.1.dist-info/RECORD
tornado_rest-0.0.1.dist-info/WHEEL
tornado_rest-0.0.1.dist-info/entry_points.txt
tornado_rest-0.0.1.dist-info/top_level.txt
