Metadata-Version: 2.1
Name: tornado-rest
Version: 0.0.1
Summary: tornado RESTful API framework.
Home-page: https://github.com/ddong8/tornado_rest
Author: ddong8
Author-email: donghaixing2010@hotmail.com
License: MIT License
Keywords: tornado RESTful API
Platform: UNKNOWN
Classifier: Development Status :: 3 - Alpha
Classifier: Intended Audience :: Developers
Classifier: Topic :: Software Development :: Build Tools
Classifier: License :: OSI Approved :: MIT License
Classifier: Programming Language :: Python :: 2
Classifier: Programming Language :: Python :: 2.6
Classifier: Programming Language :: Python :: 2.7
Classifier: Programming Language :: Python :: 3
Classifier: Programming Language :: Python :: 3.3
Classifier: Programming Language :: Python :: 3.4
Classifier: Programming Language :: Python :: 3.5
Classifier: Programming Language :: Python :: 3.6
Requires-Dist: tornado
Requires-Dist: sqlalchemy
Requires-Dist: psycopg2
Requires-Dist: six
